{
  "name": "tweetnugget",
  "display_name": "TweetNugget",
  "version": "1.2.0",
  "author": "amplifier",
  "description": "Get a random inspirational quote from curated collections of hand-picked wisdom by tech leaders, founders, and philosophers. Supports filtering by topic tags (leadership, stoicism, startups, coding, etc.) or random surprise mode. 67 quotes across 3 collections: Software Lead Weekly newsletter highlights, curated Twitter wisdom, and Stoic philosophy.",
  "category": "fun",
  "tags": ["quotes", "inspiration", "twitter", "wisdom", "motivation", "nugget", "startup", "leadership", "stoicism", "philosophy", "daily-inspiration", "software-engineering", "productivity", "mindset", "career-advice"],
  "keywords": ["quote", "inspiration", "motivation", "wisdom", "startup", "leadership", "stoic", "philosophy", "tweet", "nugget", "daily", "random", "software-lead-weekly", "curated"],
  "entry": "SKILL.md",
  "readme": "README.md",
  "license": "MIT",
  "references": [
    "references/swlw-tweets.json",
    "references/twitter-quotes.json",
    "references/stoic-quotes.json"
  ]
}
